pycocotools/__init__.py
pycocotools/_mask.cp36-win_amd64.pyd
pycocotools/coco.py
pycocotools/cocoeval.py
pycocotools/mask.py
pycocotools_win-2.0.dist-info/METADATA
pycocotools_win-2.0.dist-info/WHEEL
pycocotools_win-2.0.dist-info/top_level.txt
pycocotools_win-2.0.dist-info/RECORD
